setup.py
src/mufid/__init__.py
src/mufid/do_nothing.py
src/mufid/get_pct_change.py
src/mufid/load_json.py
src/mufid/load_pickle_object.py
src/mufid/load_yaml.py
src/mufid/mkdir.py
src/mufid/pickle_object_and_save.py
src/mufid/remove.py
src/mufid/save_yaml.py
src/mufid.egg-info/PKG-INFO
src/mufid.egg-info/SOURCES.txt
src/mufid.egg-info/dependency_links.txt
src/mufid.egg-info/top_level.txt
src/mufid/utils/__init__.py