Metadata-Version: 2.1
Name: mufid
Version: 4.2
Summary: some useful functions
Home-page: UNKNOWN
Author: Yasar Adeel Ansari
Author-email: yasaradeel@gmail.com
License: UNKNOWN
Platform: UNKNOWN
Classifier: Programming Language :: Python :: 3
Classifier: License :: OSI Approved :: MIT License
Classifier: Operating System :: OS Independent
